related_ontologies/__init__.py
related_ontologies/related.py
related_ontologies-0.2.0.dist-info/METADATA
related_ontologies-0.2.0.dist-info/WHEEL
related_ontologies-0.2.0.dist-info/licenses/LICENSE
related_ontologies-0.2.0.dist-info/RECORD
