Metadata-Version: 2.1
Name: related_ontologies
Version: 0.2.0
Summary: A package to generate related clinical ontologies (LOINC, SNOMED-CT)
Project-URL: Homepage, https://github.com/justin13601/related_ontologies
Project-URL: Bug Tracker, https://github.com/justin13601/related_ontologies/issues
Author-email: Justin Xu <justin13601@hotmail.com>
License: Copyright (c) 2022 The Python Packaging Authority
Classifier: License :: OSI Approved :: MIT License
Classifier: Operating System :: OS Independent
Classifier: Programming Language :: Python :: 3
Requires-Python: >=3.6
Requires-Dist: ftfy>=6.1.1
Requires-Dist: fuzzywuzzy>=0.18.0
Requires-Dist: jaro-winkler>=2.0.0
Requires-Dist: pandas>=1.4.3
Requires-Dist: pyyaml>=6.0
Requires-Dist: scikit-learn>=1.1.1
